{
  "id": "images_section",
  "type": "SharedSlice",
  "name": "ImagesSection",
  "description": "ImagesSection",
  "variations": [
    {
      "id": "default",
      "name": "Default",
      "docURL": "...",
      "version": "initial",
      "description": "Default",
      "imageUrl": "",
      "primary": {
        "image_1": {
          "type": "Image",
          "config": {
            "label": "Image 1",
            "constraint": {
              "width": 1080
            },
            "thumbnails": []
          }
        },
        "image_2": {
          "type": "Image",
          "config": {
            "label": "Image 2",
            "constraint": {
              "width": 1080
            },
            "thumbnails": []
          }
        },
        "caption": {
          "type": "StructuredText",
          "config": {
            "label": "Caption",
            "placeholder": "",
            "allowTargetBlank": true,
            "multi": "paragraph,strong,em,list-item,o-list-item,hyperlink"
          }
        }
      },
      "items": {}
    }
  ]
}